COPYING.md
LICENSE.md
MANIFEST.in
README.md
pyproject.toml
setup.py
cnsr/__init__.py
cnsr/install.py
cnsr/paths.py
cnsr.egg-info/PKG-INFO
cnsr.egg-info/SOURCES.txt
cnsr.egg-info/dependency_links.txt
cnsr.egg-info/entry_points.txt
cnsr.egg-info/requires.txt
cnsr.egg-info/top_level.txt
cnsr/jupyter_app_launcher/config.yaml
cnsr/notebooks/EDA.ipynb
cnsr/notebooks/ERN.ipynb
cnsr/notebooks/FAA.ipynb
cnsr/notebooks/FTT.ipynb
cnsr/notebooks/HRV.ipynb
cnsr/notebooks/RS.ipynb
tests/test_cnsr.py
tests/test_paths.py